Workbook

Sheet Albero Funzionalità Target
A1: Area Funzionale | B1: Sottoarea | C1: Funzionalità | D1: Stato | E1: Persona principale | F1: Riferimento (dominio ER / Book)
A2: 1. Piattaforma & Multi-tenancy | B2: Gestione Tenant & Organizzazioni | C2: Provisioning e gestione tenant | D2: Esistente | E2: System Admin / Tech Admin
A3: 1. Piattaforma & Multi-tenancy | B3: Gestione Tenant & Organizzazioni | C3: Configurazione e branding per tenant | D3: Esistente | E3: System Admin / Tech Admin
A4: 1. Piattaforma & Multi-tenancy | B4: Gestione Tenant & Organizzazioni | C4: Amministrazione tenant (admin) | D4: Esistente | E4: System Admin / Tech Admin
A5: 1. Piattaforma & Multi-tenancy | B5: Gestione Tenant & Organizzazioni | C5: Gestione organizzazione | D5: Esistente | E5: System Admin / Tech Admin
A6: 1. Piattaforma & Multi-tenancy | B6: Istituzioni & Gerarchia Accademica | C6: Anagrafica Istituzione (estensione del Tenant) | D6: Esistente | E6: System Admin / Tech Admin
A7: 1. Piattaforma & Multi-tenancy | B7: Istituzioni & Gerarchia Accademica | C7: College / School / Department / Program | D7: Esistente | E7: System Admin / Tech Admin
A8: 1. Piattaforma & Multi-tenancy | B8: Istituzioni & Gerarchia Accademica | C8: Workspace di istituzione | D8: Esistente | E8: System Admin / Tech Admin
A9: 1. Piattaforma & Multi-tenancy | B9: Istituzioni & Gerarchia Accademica | C9: Unità accademiche (PI1) | D9: Esistente | E9: System Admin / Tech Admin
A10: 1. Piattaforma & Multi-tenancy | B10: Amministrazione di Piattaforma | C10: Console amministrativa | D10: Esistente | E10: System Admin / Tech Admin
A11: 1. Piattaforma & Multi-tenancy | B11: Amministrazione di Piattaforma | C11: Console operatore (operator plane) | D11: Esistente | E11: System Admin / Tech Admin
A12: 1. Piattaforma & Multi-tenancy | B12: Amministrazione di Piattaforma | C12: Steward console | D12: Esistente | E12: System Admin / Tech Admin
A13: 1. Piattaforma & Multi-tenancy | B13: Amministrazione di Piattaforma | C13: Monitoraggio amministrativo | D13: Esistente | E13: System Admin / Tech Admin
... A16: 1. Piattaforma & Multi-tenancy | B16: Billing & Abbonamenti | C16: Quota e budget crediti | D16: Esistente | E16: System Admin / Tech Admin
A17: 1. Piattaforma & Multi-tenancy | B17: Guardrail & Sicurezza Tenant | C17: Policy guardrail per tenant (egress, data residency, allowlist modelli) | D17: Nuova | E17: System Admin | F17: T12 · BOOK-19 agg.
A18: 1. Piattaforma & Multi-tenancy | B18: Guardrail & Sicurezza Tenant | C18: Audit enforcement guardrail | D18: Nuova | E18: System Admin | F18: T12
A19: 2. Identità, Autenticazione & Accessi | B19: Autenticazione | C19: Registrazione, login, logout (JWT) | D19: Esistente | E19: Tech Admin
A20: 2. Identità, Autenticazione & Accessi | B20: Autenticazione | C20: Gestione e reset password | D20: Esistente | E20: Tech Admin
A21: 2. Identità, Autenticazione & Accessi | B21: Autenticazione | C21: Autenticazione avanzata / sessioni | D21: Esistente | E21: Tech Admin
A22: 2. Identità, Autenticazione & Accessi | B22: Single Sign-On & Federazione | C22: SAML / Shibboleth | D22: Esistente | E22: Tech Admin
A23: 2. Identità, Autenticazione & Accessi | B23: Single Sign-On & Federazione | C23: OIDC | D23: Esistente | E23: Tech Admin
A24: 2. Identità, Autenticazione & Accessi | B24: Single Sign-On & Federazione | C24: Federazione identità | D24: Esistente | E24: Tech Admin
A25: 2. Identità, Autenticazione & Accessi | B25: Single Sign-On & Federazione | C25: LTI 1.3 / piattaforme LTI | D25: Esistente | E25: Tech Admin
A26: 2. Identità, Autenticazione & Accessi | B26: Single Sign-On & Federazione | C26: SPID (via Keycloak) — profilo italiano | D26: Esistente | E26: Tech Admin
A27: 2. Identità, Autenticazione & Accessi | B27: Autorizzazione & Ruoli | C27: RBAC (ruoli e permessi) | D27: Esistente | E27: Tech Admin
A28: 2. Identità, Autenticazione & Accessi | B28: Autorizzazione & Ruoli | C28: Inviti utente | D28: Esistente | E28: Tech Admin
A29: 2. Identità, Autenticazione & Accessi | B29: Autorizzazione & Ruoli | C29: Profilo utente e preferenze | D29: Esistente | E29: Tech Admin
A30: 2. Identità, Autenticazione & Accessi | B30: Autorizzazione & Ruoli | C30: Attivazione / disattivazione utenti | D30: Esistente | E30: Tech Admin
... A47: 3. Authoring & Gestione Corsi | B47: Interscambio Corsi | C47: Import legacy (PPTX/PDF → corso strutturato) | D47: Esistente | E47: Teacher / Dean
A48: 3. Authoring & Gestione Corsi | B48: Ciclo di Vita & Workflow Editoriale | C48: Workflow di approvazione edizione catalogo (Dean→Provost, firma QES) | D48: Nuova | E48: Dean / Provost | F48: T6 · BOOK-24
A49: 3. Authoring & Gestione Corsi | B49: Struttura del Corso | C49: Lineage incarico→corso (authoring engagement) | D49: Nuova | E49: Teacher | F49: T4 · BOOK-22
A50: 4. Generazione AI di Contenuti & Media | B50: Generazione Corsi AI | C50: Course Factory (generazione da syllabus / file) | D50: Esistente | E50: Teacher
A51: 4. Generazione AI di Contenuti & Media | B51: Generazione Corsi AI | C51: Pipeline import legacy (3 fasi con gate di review) | D51: Esistente | E51: Teacher
A52: 4. Generazione AI di Contenuti & Media | B52: Generazione Corsi AI | C52: Architetto del corso / planner legacy→DLU | D52: Esistente | E52: Teacher
A53: 4. Generazione AI di Contenuti & Media | B53: Enrichment Multimediale | C53: Generazione immagini | D53: Esistente | E53: Teacher
A54: 4. Generazione AI di Contenuti & Media | B54: Enrichment Multimediale | C54: Generazione audio / TTS | D54: Esistente | E54: Teacher
A55: 4. Generazione AI di Contenuti & Media | B55: Enrichment Multimediale | C55: Generazione e gestione video | D55: Esistente | E55: Teacher
A56: 4. Generazione AI di Contenuti & Media | B56: Enrichment Multimediale | C56: Avatar Studio / Video Professor (HeyGen) | D56: Esistente | E56: Teacher
A57: 4. Generazione AI di Contenuti & Media | B57: Enrichment Multimediale | C57: Trascrizione | D57: Esistente | E57: Teacher
A58: 4. Generazione AI di Contenuti & Media | B58: Contenuti Interattivi | C58: Generazione quiz | D58: Esistente | E58: Teacher
A59: 4. Generazione AI di Contenuti & Media | B59: Contenuti Interattivi | C59: Generazione lab / codice | D59: Esistente | E59: Teacher
A60: 4. Generazione AI di Contenuti & Media | B60: Contenuti Interattivi | C60: Espansione e variazione testo | D60: Esistente | E60: Teacher
A61: 4. Generazione AI di Contenuti & Media | B61: RAG & Grounding | C61: Pipeline RAG | D61: Esistente | E61: Teacher
... A74: 5. AI Governance & LLM Management | B74: Agenti & Orchestrazione | C74: Workflow orchestrator | D74: Esistente | E74: Admin AI Engineering
A75: 5. AI Governance & LLM Management | B75: Governance AI | C75: Eval harness: dataset golden, run, GA gate pre-release | D75: Nuova | E75: Admin AI Engineering | F75: T11 · BOOK-11 agg.
A76: 5. AI Governance & LLM Management | B76: Governance AI | C76: Versionamento e rollout controllato di preset/prompt | D76: Nuova | E76: Admin AI Engineering | F76: T11
A77: 5. AI Governance & LLM Management | B77: Agenti & Orchestrazione | C77: Agente Student Companion consolidato (missioni, nudging, obiettivi — propose-only) | D77: Nuova | E77: Student / Admin AI Eng | F77: BOOK-10A+ · NEW-31
A78: 5. AI Governance & LLM Management | B78: Agenti & Orchestrazione | C78: Agente Faculty Assistant (authoring, teaching ops, registro — propose-only) | D78: Nuova | E78: Teacher / Admin AI Eng | F78: BOOK-10A+ · NEW-31
A79: 5. AI Governance & LLM Management | B79: Agenti & Orchestrazione | C79: Agente Admin Copilot back-office (pratiche, certificati, fascicoli) | D79: Nuova | E79: BackOffice / Admin AI Eng | F79: BOOK-10A+ · NEW-31
A80: 5. AI Governance & LLM Management | B80: Agenti & Orchestrazione | C80: Agente CFO Analyst (narrative variance/forecast, propose-only) | D80: Nuova | E80: CFO / Admin AI Eng | F80: BOOK-10A+ · NEW-31
A81: 6. Knowledge Graph & Ontologia | B81: Costruzione del Grafo | C81: Estrazione NLP dei concetti | D81: Esistente | E81: Dean / Admin AI Eng
A82: 6. Knowledge Graph & Ontologia | B82: Costruzione del Grafo | C82: Build & sync del Knowledge Graph (Neo4j) | D82: Esistente | E82: Dean / Admin AI Eng
A83: 6. Knowledge Graph & Ontologia | B83: Costruzione del Grafo | C83: Event bus / overlay sync | D83: Esistente | E83: Dean / Admin AI Eng
A84: 6. Knowledge Graph & Ontologia | B84: Interrogazione & Ontologia | C84: Query sul grafo | D84: Esistente | E84: Dean / Admin AI Eng
A85: 6. Knowledge Graph & Ontologia | B85: Interrogazione & Ontologia | C85: Ontologia (registry dlu-core.yaml) | D85: Esistente | E85: Dean / Admin AI Eng
A86: 6. Knowledge Graph & Ontologia | B86: Interrogazione & Ontologia | C86: Grafo delle competenze | D86: Esistente | E86: Dean / Admin AI Eng
A87: 6. Knowledge Graph & Ontologia | B87: Interrogazione & Ontologia | C87: Export del grafo | D87: Esistente | E87: Dean / Admin AI Eng
A88: 6. Knowledge Graph & Ontologia | B88: Applicazioni | C88: Curriculum map | D88: Esistente | E88: Dean / Admin AI Eng
A89: 6. Knowledge Graph & Ontologia | B89: Applicazioni | C89: Ricerca semantica / raccomandazione concetti | D89: Esistente | E89: Dean / Admin AI Eng
A90: 7. Learning Outcomes & Curriculum | B90: Learning Outcomes | C90: ILO / PLO / CLO e allineamenti | D90: Esistente | E90: Dean / Provost
A91: 7. Learning Outcomes & Curriculum | B91: Learning Outcomes | C91: Framework degli outcome (PI1) | D91: Esistente | E91: Dean / Provost
A92: 7. Learning Outcomes & Curriculum | B92: Learning Outcomes | C92: Allineamento outcome (QA) | D92: Esistente | E92: Dean / Provost
... A99: 7. Learning Outcomes & Curriculum | B99: Competenze | C99: Crosswalk ESCO | D99: Esistente | E99: Dean / Provost
A100: 7. Learning Outcomes & Curriculum | B100: Curriculum & Programmi | C100: Program knowledge map (grafo aggregato con copertura PLO) | D100: Nuova | E100: Dean | F100: T6
A101: 8. Assessment & Valutazione | B101: Prove & Quiz | C101: Quiz (creazione ed erogazione) | D101: Esistente | E101: Teacher / Student
A102: 8. Assessment & Valutazione | B102: Prove & Quiz | C102: Feedback sui quiz | D102: Esistente | E102: Teacher / Student
A103: 8. Assessment & Valutazione | B103: Prove & Quiz | C103: Generazione quiz per livello di Bloom | D103: Esistente | E103: Teacher / Student
A104: 8. Assessment & Valutazione | B104: Prove & Quiz | C104: Esami finali e tentativi d'esame | D104: Esistente | E104: Teacher / Student
A105: 8. Assessment & Valutazione | B105: Sessioni & Evidenze | C105: Sessioni di assessment | D105: Esistente | E105: Teacher / Student
A106: 8. Assessment & Valutazione | B106: Sessioni & Evidenze | C106: Agente di assessment | D106: Esistente | E106: Teacher / Student
A107: 8. Assessment & Valutazione | B107: Sessioni & Evidenze | C107: Evidenze di valutazione | D107: Esistente | E107: Teacher / Student
A108: 8. Assessment & Valutazione | B108: Sessioni & Evidenze | C108: Calibrazione degli item | D108: Esistente | E108: Teacher / Student
A109: 8. Assessment & Valutazione | B109: Valutazione & Qualità | C109: Grading | D109: Esistente | E109: Teacher / Student
A110: 8. Assessment & Valutazione | B110: Valutazione & Qualità | C110: Pre-valutazione (staff) | D110: Esistente | E110: Teacher / Student
A111: 8. Assessment & Valutazione | B111: Valutazione & Qualità | C111: Rilevazione plagio | D111: Esistente | E111: Teacher / Student
A112: 8. Assessment & Valutazione | B112: Valutazione & Qualità | C112: Serializzazione QTI | D112: Esistente | E112: Teacher / Student
A113: 8. Assessment & Valutazione | B113: Prove & Quiz | C113: Pre-valutazione diagnostica delle conoscenze (baseline knowledge map) | D113: Nuova | E113: Student | F113: T2 · BOOK-06 agg.
A114: 9. Personalizzazione & Apprendimento Adattivo | B114: Mastery & Progressione | C114: Mastery tracking (BKT) | D114: Esistente | E114: Student
A115: 9. Personalizzazione & Apprendimento Adattivo | B115: Mastery & Progressione | C115: Knowledge mastery | D115: Esistente | E115: Student
A116: 9. Personalizzazione & Apprendimento Adattivo | B116: Mastery & Progressione | C116: Ripetizione dilazionata (spaced repetition) | D116: Esistente | E116: Student
A117: 9. Personalizzazione & Apprendimento Adattivo | B117: Pacing & Percorsi | C117: Pacing del corso (base ed enhanced) | D117: Esistente | E117: Student
A118: 9. Personalizzazione & Apprendimento Adattivo | B118: Pacing & Percorsi | C118: Academic GPS (navigazione del percorso) | D118: Esistente | E118: Student
A119: 9. Personalizzazione & Apprendimento Adattivo | B119: Pacing & Percorsi | C119: Route graph compiler | D119: Esistente | E119: Student
A120: 9. Personalizzazione & Apprendimento Adattivo | B120: Tutoraggio & Coaching AI | C120: Pedagogical coach | D120: Esistente | E120: Student
A121: 9. Personalizzazione & Apprendimento Adattivo | B121: Tutoraggio & Coaching AI | C121: Subject tutor / tutor dialogue | D121: Esistente | E121: Student
A122: 9. Personalizzazione & Apprendimento Adattivo | B122: Tutoraggio & Coaching AI | C122: Raccomandazioni (recommendation engine v2) | D122: Esistente | E122: Student
A123: 9. Personalizzazione & Apprendimento Adattivo | B123: Modello dello Studente | C123: Profilo learner | D123: Esistente | E123: Student
A124: 9. Personalizzazione & Apprendimento Adattivo | B124: Modello dello Studente | C124: Student twin / gemello digitale | D124: Esistente | E124: Student
A125: 9. Personalizzazione & Apprendimento Adattivo | B125: Modello dello Studente | C125: Rilevazione crisi / etiquette del coach | D125: Esistente | E125: Student
A126: 9. Personalizzazione & Apprendimento Adattivo | B126: Modello dello Studente | C126: Key objective contrattualizzato con revisioni periodiche | D126: Nuova | E126: Student | F126: T2
A127: 9. Personalizzazione & Apprendimento Adattivo | B127: Pacing & Percorsi | C127: Missioni di studio giornaliere (triade Canvas·Companion·Missions) | D127: Nuova | E127: Student | F127: T2 · BOOK-17 agg.
A128: 9. Personalizzazione & Apprendimento Adattivo | B128: Tutoraggio & Coaching AI | C128: Engine proattivo di retention e nudging (segnali di disimpegno) | D128: Nuova | E128: Student | F128: Piano SaaS EdTech
A129: 10. Esperienza Studente & Lifecycle | B129: Iscrizioni & Progresso | C129: Iscrizioni (enrollment domain) | D129: Esistente | E129: Student
A130: 10. Esperienza Studente & Lifecycle | B130: Iscrizioni & Progresso | C130: Coorti | D130: Esistente | E130: Student
A131: 10. Esperienza Studente & Lifecycle | B131: Iscrizioni & Progresso | C131: Tracciamento progresso | D131: Esistente | E131: Student
A132: 10. Esperienza Studente & Lifecycle | B132: Community & Interazione | C132: Community / post | D132: Esistente | E132: Student
A133: 10. Esperienza Studente & Lifecycle | B133: Community & Interazione | C133: Forum | D133: Esistente | E133: Student
A134: 10. Esperienza Studente & Lifecycle | B134: Community & Interazione | C134: Notifiche | D134: Esistente | E134: Student
A135: 10. Esperienza Studente & Lifecycle | B135: Community & Interazione | C135: Feedback | D135: Esistente | E135: Student
A136: 10. Esperienza Studente & Lifecycle | B136: Wallet & Mobilità | C136: Credential wallet studente | D136: Esistente | E136: Student
...

Sheet Riepilogo Aree
A1: Area Funzionale | B1: Totale | C1: Esistenti | D1: Estensioni | E1: Nuove
A2: 1. Piattaforma & Multi-tenancy | B2: =COUNTIF('Albero Funzionalità Target'!$A$2:$A$1000,A2) | C2: =COUNTIFS('Albero Funzionalità Target'!$A$2:$A$1000,A2,'Albero Funzionalità Target'!$D$2:$D$1000,"Esistente") | D2: =COUNTIFS('Albero Funzionalità Target'!$A$2:$A$1000,A2,'Albero Funzionalità Target'!$D$2:$D$1000,"Estensione") | E2: =COUNTIFS('Albero Funzionalità Target'!$A$2:$A$1000,A2,'Albero Funzionalità Target'!$D$2:$D$1000,"Nuova")
A3: 2. Identità, Autenticazione & Accessi | B3: =COUNTIF('Albero Funzionalità Target'!$A$2:$A$1000,A3) | C3: =COUNTIFS('Albero Funzionalità Target'!$A$2:$A$1000,A3,'Albero Funzionalità Target'!$D$2:$D$1000,"Esistente") | D3: =COUNTIFS('Albero Funzionalità Target'!$A$2:$A$1000,A3,'Albero Funzionalità Target'!$D$2:$D$1000,"Estensione") | E3: =COUNTIFS('Albero Funzionalità Target'!$A$2:$A$1000,A3,'Albero Funzionalità Target'!$D$2:$D$1000,"Nuova")
A4: 3. Authoring & Gestione Corsi | B4: =COUNTIF('Albero Funzionalità Target'!$A$2:$A$1000,A4) | C4: =COUNTIFS('Albero Funzionalità Target'!$A$2:$A$1000,A4,'Albero Funzionalità Target'!$D$2:$D$1000,"Esistente") | D4: =COUNTIFS('Albero Funzionalità Target'!$A$2:$A$1000,A4,'Albero Funzionalità Target'!$D$2:$D$1000,"Estensione") | E4: =COUNTIFS('Albero Funzionalità Target'!$A$2:$A$1000,A4,'Albero Funzionalità Target'!$D$2:$D$1000,"Nuova")
A5: 4. Generazione AI di Contenuti & Media | B5: =COUNTIF('Albero Funzionalità Target'!$A$2:$A$1000,A5) | C5: =COUNTIFS('Albero Funzionalità Target'!$A$2:$A$1000,A5,'Albero Funzionalità Target'!$D$2:$D$1000,"Esistente") | D5: =COUNTIFS('Albero Funzionalità Target'!$A$2:$A$1000,A5,'Albero Funzionalità Target'!$D$2:$D$1000,"Estensione") | E5: =COUNTIFS('Albero Funzionalità Target'!$A$2:$A$1000,A5,'Albero Funzionalità Target'!$D$2:$D$1000,"Nuova")
A6: 5. AI Governance & LLM Management | B6: =COUNTIF('Albero Funzionalità Target'!$A$2:$A$1000,A6) | C6: =COUNTIFS('Albero Funzionalità Target'!$A$2:$A$1000,A6,'Albero Funzionalità Target'!$D$2:$D$1000,"Esistente") | D6: =COUNTIFS('Albero Funzionalità Target'!$A$2:$A$1000,A6,'Albero Funzionalità Target'!$D$2:$D$1000,"Estensione") | E6: =COUNTIFS('Albero Funzionalità Target'!$A$2:$A$1000,A6,'Albero Funzionalità Target'!$D$2:$D$1000,"Nuova")
A7: 6. Knowledge Graph & Ontologia | B7: =COUNTIF('Albero Funzionalità Target'!$A$2:$A$1000,A7) | C7: =COUNTIFS('Albero Funzionalità Target'!$A$2:$A$1000,A7,'Albero Funzionalità Target'!$D$2:$D$1000,"Esistente") | D7: =COUNTIFS('Albero Funzionalità Target'!$A$2:$A$1000,A7,'Albero Funzionalità Target'!$D$2:$D$1000,"Estensione") | E7: =COUNTIFS('Albero Funzionalità Target'!$A$2:$A$1000,A7,'Albero Funzionalità Target'!$D$2:$D$1000,"Nuova")
A8: 7. Learning Outcomes & Curriculum | B8: =COUNTIF('Albero Funzionalità Target'!$A$2:$A$1000,A8) | C8: =COUNTIFS('Albero Funzionalità Target'!$A$2:$A$1000,A8,'Albero Funzionalità Target'!$D$2:$D$1000,"Esistente") | D8: =COUNTIFS('Albero Funzionalità Target'!$A$2:$A$1000,A8,'Albero Funzionalità Target'!$D$2:$D$1000,"Estensione") | E8: =COUNTIFS('Albero Funzionalità Target'!$A$2:$A$1000,A8,'Albero Funzionalità Target'!$D$2:$D$1000,"Nuova")
A9: 8. Assessment & Valutazione | B9: =COUNTIF('Albero Funzionalità Target'!$A$2:$A$1000,A9) | C9: =COUNTIFS('Albero Funzionalità Target'!$A$2:$A$1000,A9,'Albero Funzionalità Target'!$D$2:$D$1000,"Esistente") | D9: =COUNTIFS('Albero Funzionalità Target'!$A$2:$A$1000,A9,'Albero Funzionalità Target'!$D$2:$D$1000,"Estensione") | E9: =COUNTIFS('Albero Funzionalità Target'!$A$2:$A$1000,A9,'Albero Funzionalità Target'!$D$2:$D$1000,"Nuova")
A10: 9. Personalizzazione & Apprendimento Adattivo | B10: =COUNTIF('Albero Funzionalità Target'!$A$2:$A$1000,A10) | C10: =COUNTIFS('Albero Funzionalità Target'!$A$2:$A$1000,A10,'Albero Funzionalità Target'!$D$2:$D$1000,"Esistente") | D10: =COUNTIFS('Albero Funzionalità Target'!$A$2:$A$1000,A10,'Albero Funzionalità Target'!$D$2:$D$1000,"Estensione") | E10: =COUNTIFS('Albero Funzionalità Target'!$A$2:$A$1000,A10,'Albero Funzionalità Target'!$D$2:$D$1000,"Nuova")
A11: 10. Esperienza Studente & Lifecycle | B11: =COUNTIF('Albero Funzionalità Target'!$A$2:$A$1000,A11) | C11: =COUNTIFS('Albero Funzionalità Target'!$A$2:$A$1000,A11,'Albero Funzionalità Target'!$D$2:$D$1000,"Esistente") | D11: =COUNTIFS('Albero Funzionalità Target'!$A$2:$A$1000,A11,'Albero Funzionalità Target'!$D$2:$D$1000,"Estensione") | E11: =COUNTIFS('Albero Funzionalità Target'!$A$2:$A$1000,A11,'Albero Funzionalità Target'!$D$2:$D$1000,"Nuova")
A12: 11. Faculty & Staff | B12: =COUNTIF('Albero Funzionalità Target'!$A$2:$A$1000,A12) | C12: =COUNTIFS('Albero Funzionalità Target'!$A$2:$A$1000,A12,'Albero Funzionalità Target'!$D$2:$D$1000,"Esistente") | D12: =COUNTIFS('Albero Funzionalità Target'!$A$2:$A$1000,A12,'Albero Funzionalità Target'!$D$2:$D$1000,"Estensione") | E12: =COUNTIFS('Albero Funzionalità Target'!$A$2:$A$1000,A12,'Albero Funzionalità Target'!$D$2:$D$1000,"Nuova")
A13: 12. Credenziali, Badge & Riconoscimenti | B13: =COUNTIF('Albero Funzionalità Target'!$A$2:$A$1000,A13) | C13: =COUNTIFS('Albero Funzionalità Target'!$A$2:$A$1000,A13,'Albero Funzionalità Target'!$D$2:$D$1000,"Esistente") | D13: =COUNTIFS('Albero Funzionalità Target'!$A$2:$A$1000,A13,'Albero Funzionalità Target'!$D$2:$D$1000,"Estensione") | E13: =COUNTIFS('Albero Funzionalità Target'!$A$2:$A$1000,A13,'Albero Funzionalità Target'!$D$2:$D$1000,"Nuova")
... A27: 26. Accreditamento & Assicurazione Qualità (DM 1154/2021) | B27: =COUNTIF('Albero Funzionalità Target'!$A$2:$A$1000,A27) | C27: =COUNTIFS('Albero Funzionalità Target'!$A$2:$A$1000,A27,'Albero Funzionalità Target'!$D$2:$D$1000,"Esistente") | D27: =COUNTIFS('Albero Funzionalità Target'!$A$2:$A$1000,A27,'Albero Funzionalità Target'!$D$2:$D$1000,"Estensione") | E27: =COUNTIFS('Albero Funzionalità Target'!$A$2:$A$1000,A27,'Albero Funzionalità Target'!$D$2:$D$1000,"Nuova")
A28: TOTALE | B28: =SUM(B2:B27) | C28: =SUM(C2:C27) | D28: =SUM(D2:D27) | E28: =SUM(E2:E27)

Sheet Legenda
A1: Campo | B1: Descrizione
A2: Stato = Esistente | B2: Funzionalità già presente nell MVP dlu_builder_tk (da ALBERO_FUNZIONALITA.xlsx, 27/07/2026)
A3: Stato = Estensione | B3: Funzionalità esistente da estendere per il target (celle gialle)
A4: Stato = Nuova | B4: Funzionalità mancante, da realizzare per il target (celle azzurre)
A5: Persona principale | B5: Per le righe esistenti è un default per area; per le nuove è puntuale
A6: Riferimento | B6: T1–T14 = domini in ER_MAP_TARGET.md · BOOK-xx = volume masterbook (21–26, alcuni in draft)
